quarticequation/__init__.py
quarticequation/__main__.py
quarticequation/quarticcmd.py
quarticequation/quarticequation.py
quarticequation/version.py
quarticequation-0.0.3.dist-info/METADATA
quarticequation-0.0.3.dist-info/WHEEL
quarticequation-0.0.3.dist-info/licenses/LICENSE
quarticequation-0.0.3.dist-info/RECORD
