Metadata-Version: 2.4
Name: quarticequation
Version: 0.0.3
Summary: A Python module for the exact solutions of a quartic equation
Project-URL: Homepage, https://github.com/SWVandenEnden/
Project-URL: Repository, https://github.com/SWVandenEnden/quarticequation
Author: Gien van den Enden
Author-email: swvandenenden@gmail.com
Maintainer-email: Gien van den Enden <swvandenenden@gmail.com>
License: GNU General Public License v3 or later (GPLv3+)
License-File: LICENSE
Keywords: math,quartic equation,symbolic
Classifier: Development Status :: 4 - Beta
Classifier: Intended Audience :: Developers
Classifier: Intended Audience :: Education
Classifier: Intended Audience :: Science/Research
Classifier: Operating System :: OS Independent
Classifier: Programming Language :: Python :: 3
Classifier: Topic :: Scientific/Engineering :: Mathematics
Requires-Python: >=3.11
Requires-Dist: symexpress3>=0.0.12
